manticoresearch/__init__.py
manticoresearch/api_client.py
manticoresearch/configuration.py
manticoresearch/exceptions.py
manticoresearch/model_utils.py
manticoresearch/rest.py
manticoresearch/api/__init__.py
manticoresearch/api/index_api.py
manticoresearch/api/search_api.py
manticoresearch/api/utils_api.py
manticoresearch/apis/__init__.py
manticoresearch/model/__init__.py
manticoresearch/model/aggregation.py
manticoresearch/model/aggregation_sort_inner_value.py
manticoresearch/model/aggregation_terms.py
manticoresearch/model/attr_filter.py
manticoresearch/model/bool_filter.py
manticoresearch/model/bulk_response.py
manticoresearch/model/delete_document_request.py
manticoresearch/model/delete_response.py
manticoresearch/model/equals_filter.py
manticoresearch/model/error_response.py
manticoresearch/model/facet.py
manticoresearch/model/filter_boolean.py
manticoresearch/model/filter_number.py
manticoresearch/model/filter_string.py
manticoresearch/model/fulltext_filter.py
manticoresearch/model/geo_distance_filter.py
manticoresearch/model/geo_distance_filter_location_anchor.py
manticoresearch/model/highlight.py
manticoresearch/model/highlight_field.py
manticoresearch/model/in_filter.py
manticoresearch/model/insert_document_request.py
manticoresearch/model/knn_query_by_doc_id.py
manticoresearch/model/knn_query_by_vector.py
manticoresearch/model/match_filter.py
manticoresearch/model/match_op.py
manticoresearch/model/match_op_filter.py
manticoresearch/model/match_phrase_filter.py
manticoresearch/model/not_filter_boolean.py
manticoresearch/model/not_filter_number.py
manticoresearch/model/not_filter_string.py
manticoresearch/model/option.py
manticoresearch/model/percolate_request.py
manticoresearch/model/percolate_request_query.py
manticoresearch/model/query_filter.py
manticoresearch/model/range_filter.py
manticoresearch/model/replace_document_request.py
manticoresearch/model/search_request.py
manticoresearch/model/search_request_knn.py
manticoresearch/model/search_response.py
manticoresearch_dev-4.1.24031114.dist-info/LICENSE.txt
manticoresearch_dev-4.1.24031114.dist-info/METADATA
manticoresearch_dev-4.1.24031114.dist-info/WHEEL
manticoresearch_dev-4.1.24031114.dist-info/top_level.txt
manticoresearch_dev-4.1.24031114.dist-info/RECORD
