Metadata-Version: 2.1
Name: manticoresearch-dev
Version: 4.1.24031114
Summary: Python client for Manticore Search
Home-page: 
Author: Manticore Software Ltd.
Author-email: info@manticoresearch.com
License: MIT
Project-URL: Documentation, https://github.com/manticoresoftware/manticoresearch-python/tree/master/docs
Project-URL: Source Code, https://github.com/manticoresoftware/manticoresearch-python
Project-URL: Issue Tracker, https://github.com/manticoresoftware/manticoresearch-python/issues
Keywords: full-text search,manticoresearch,search
Classifier: License :: OSI Approved :: Apache Software License
Classifier: Intended Audience :: Developers
Classifier: Operating System :: OS Independent
Classifier: Programming Language :: Python
Classifier: Programming Language :: Python :: 2
Classifier: Programming Language :: Python :: 2.7
Classifier: Programming Language :: Python :: 3
Classifier: Programming Language :: Python :: 3.4
Classifier: Programming Language :: Python :: 3.5
Classifier: Programming Language :: Python :: 3.6
Classifier: Programming Language :: Python :: 3.7
Classifier: Programming Language :: Python :: 3.8
Classifier: Topic :: Internet
Classifier: Topic :: Internet :: WWW/HTTP
Classifier: Topic :: Internet :: WWW/HTTP :: Indexing/Search
License-File: LICENSE.txt
Requires-Dist: urllib3 >=1.15
Requires-Dist: six >=1.10
Requires-Dist: certifi
Requires-Dist: python-dateutil
